.editorconfig
LICENSE
MANIFEST.in
Makefile
README.rst
setup.cfg
setup.py
QBorg.egg-info/PKG-INFO
QBorg.egg-info/SOURCES.txt
QBorg.egg-info/dependency_links.txt
QBorg.egg-info/entry_points.txt
QBorg.egg-info/requires.txt
QBorg.egg-info/top_level.txt
icons/qborg-1024x1024.png
icons/qborg-128x128.png
icons/qborg-16x16.png
icons/qborg-192x192.png
icons/qborg-22x22.png
icons/qborg-24x24.png
icons/qborg-256x256.png
icons/qborg-32x32.png
icons/qborg-48x48.png
icons/qborg-512x512.png
icons/qborg-64x64.png
icons/qborg-72x72.png
icons/qborg-96x96.png
icons/qborg.svg
qborg/__init__.py
qborg/__main__.py
qborg/qborg.py
qborg/adapters/__init__.py
qborg/adapters/backingstore/__init__.py
qborg/adapters/backingstore/file.py
qborg/adapters/backup/__init__.py
qborg/adapters/backup/borg/__init__.py
qborg/adapters/backup/borg/borg11adapter.py
qborg/adapters/backup/borg/iodelegate.py
qborg/entities/backup.py
qborg/entities/backupitem.py
qborg/entities/command.py
qborg/entities/config.py
qborg/entities/job.py
qborg/entities/location.py
qborg/entities/repository.py
qborg/logic/askpassdelegate.py
qborg/logic/config_file_manager.py
qborg/logic/controllerdelegate.py
qborg/logic/createbackup.py
qborg/logic/deletebackup.py
qborg/logic/deleterepo.py
qborg/logic/detection.py
qborg/logic/extractbackup.py
qborg/logic/factories.py
qborg/logic/initrepo.py
qborg/logic/listbackup.py
qborg/logic/listrepo.py
qborg/logic/renamebackup.py
qborg/logic/wrapperdelegate.py
qborg/ui/__init__.py
qborg/ui/pyqt4/Makefile
qborg/ui/pyqt4/__init__.py
qborg/ui/pyqt4/app.py
qborg/ui/pyqt4/resources.py
qborg/ui/pyqt4/controllers/__init__.py
qborg/ui/pyqt4/controllers/createbackupcontroller.py
qborg/ui/pyqt4/controllers/deletebackupcontroller.py
qborg/ui/pyqt4/controllers/deleterepocontroller.py
qborg/ui/pyqt4/controllers/extractbackupcontroller.py
qborg/ui/pyqt4/controllers/initrepocontroller.py
qborg/ui/pyqt4/controllers/listbackupcontroller.py
qborg/ui/pyqt4/controllers/listrepocontroller.py
qborg/ui/pyqt4/controllers/maincontroller.py
qborg/ui/pyqt4/controllers/renamebackupcontroller.py
qborg/ui/pyqt4/controllers/renamerepocontroller.py
qborg/ui/pyqt4/forms/create_backup.ui
