Metadata-Version: 2.1
Name: QBorg
Version: 0.0.1.dev1
Summary: An easy to use encrypting, deduplicating backup software.
Home-page: https://github.engineering.zhaw.ch/QBorg/QBorg
Author: The QBorg team
Author-email: qborg@qborg.rocks
Maintainer: The QBorg team
Maintainer-email: maintainer@qborg.rocks
License: GPLv3
Keywords: borg backup restore gui qt
Platform: UNKNOWN
Classifier: Development Status :: 3 - Alpha
Classifier: Environment :: X11 Applications :: Qt
Classifier: Intended Audience :: End Users/Desktop
Classifier: Intended Audience :: System Administrators
Classifier: License :: OSI Approved :: GNU General Public License v3 (GPLv3)
Classifier: Programming Language :: Python :: 3
Classifier: Programming Language :: Python :: 3.4
Classifier: Programming Language :: Python :: 3.5
Classifier: Programming Language :: Python :: 3.6
Classifier: Programming Language :: Python :: 3.7
Classifier: Topic :: System :: Archiving
Classifier: Topic :: System :: Archiving :: Backup
Requires-Python: >=3.4
Provides-Extra: docs
Provides-Extra: dev
